IFConnectOld/InfiniteFlightConnectOld.py
IFConnectOld/__init__.py
IFConnectOld-1.0.4.dist-info/LICENSE
IFConnectOld-1.0.4.dist-info/METADATA
IFConnectOld-1.0.4.dist-info/WHEEL
IFConnectOld-1.0.4.dist-info/top_level.txt
IFConnectOld-1.0.4.dist-info/RECORD
