Metadata-Version: 2.1
Name: IFConnectOld
Version: 1.0.4
Summary: A module using python to connect to the Infinite Flight Connect API v1
Home-page: https://github.com/flyme2bluemoon/InfiniteFlightConnect-Python
Author: Matthew Shen
Author-email: flyme2bluemoon@wearehackerone.com
License: UNKNOWN
Platform: UNKNOWN
Classifier: Programming Language :: Python :: 3.5
Classifier: Operating System :: OS Independent
Requires-Python: >=3.0
